obsidian/__init__.py
obsidian/enums.py
obsidian/errors.py
obsidian/events.py
obsidian/filters.py
obsidian/http.py
obsidian/mixin.py
obsidian/node.py
obsidian/player.py
obsidian/pool.py
obsidian/queue.py
obsidian/search.py
obsidian/spotify.py
obsidian/stats.py
obsidian/track.py
obsidian/websocket.py
obsidian.py-0.3.0.dist-info/LICENSE
obsidian.py-0.3.0.dist-info/METADATA
obsidian.py-0.3.0.dist-info/WHEEL
obsidian.py-0.3.0.dist-info/top_level.txt
obsidian.py-0.3.0.dist-info/RECORD
