Metadata-Version: 2.1
Name: obsidian.py
Version: 0.3.0
Summary: A wrapper around Obsidian's REST and Websocket API.
Home-page: https://github.com/jay3332/obsidian.py
Author: jay3332
License: MIT
Project-URL: Issue tracker, https://github.com/jay3332/obsidian.py/issues
Platform: UNKNOWN
Classifier: License :: OSI Approved :: MIT License
Classifier: Intended Audience :: Developers
Classifier: Natural Language :: English
Classifier: Operating System :: OS Independent
Classifier: Programming Language :: Python :: 3.7
Classifier: Programming Language :: Python :: 3.8
Classifier: Programming Language :: Python :: 3.9
Classifier: Topic :: Internet
Classifier: Topic :: Software Development :: Libraries
Classifier: Topic :: Software Development :: Libraries :: Python Modules
Classifier: Topic :: Utilities
Requires-Python: >=3.7.0
Requires-Dist: discord.py (>=1.6.0)
Requires-Dist: aiohttp (<3.8.0,>=3.6.0)
Provides-Extra: docs
Requires-Dist: sphinx (>=4.0.2) ; extra == 'docs'
Requires-Dist: karma-sphinx-theme (>=0.0.8) ; extra == 'docs'
Requires-Dist: sphinxcontrib-asyncio (>=0.3.0) ; extra == 'docs'
Requires-Dist: sphinx-nervproject-theme (>=2.0.4) ; extra == 'docs'
